pykalman/__init__.py
pykalman/standard.py
pykalman/unscented.py
pykalman/utils.py
pykalman/datasets/__init__.py
pykalman/datasets/base.py
pykalman/datasets/data/robot.mat
pykalman/datasets/descr/robot.rst
pykalman/sqrt/__init__.py
pykalman/sqrt/bierman.py
pykalman/sqrt/cholesky.py
pykalman/sqrt/unscented.py
pykalman/sqrt/tests/__init__.py
pykalman/sqrt/tests/test_bierman.py
pykalman/sqrt/tests/test_cholesky.py
pykalman/sqrt/tests/test_unscented.py
pykalman/tests/__init__.py
pykalman/tests/test_standard.py
pykalman/tests/test_unscented.py
pykalman_py311_update-0.9.6.dist-info/COPYING
pykalman_py311_update-0.9.6.dist-info/METADATA
pykalman_py311_update-0.9.6.dist-info/WHEEL
pykalman_py311_update-0.9.6.dist-info/top_level.txt
pykalman_py311_update-0.9.6.dist-info/RECORD
