Metadata-Version: 2.1
Name: pykalman-py311-update
Version: 0.9.6
Summary: An implementation of the Kalman Filter, Kalman Smoother, and EM algorithm in Python
Home-page: http://pykalman.github.com
Author: Daniel Duckworth
Author-email: pykalman@gmail.com
License: BSD
Keywords: kalman filter smoothing em hmm tracking unscented ukf kf
Classifier: Development Status :: 4 - Beta
Classifier: Intended Audience :: Science/Research
Classifier: License :: OSI Approved :: BSD License
Classifier: Operating System :: OS Independent
Classifier: Programming Language :: Python
Classifier: Programming Language :: Python :: 3
Classifier: Topic :: Scientific/Engineering :: Artificial Intelligence
License-File: COPYING
Requires-Dist: numpy
Requires-Dist: scipy
Provides-Extra: docs
Requires-Dist: Sphinx ; extra == 'docs'
Requires-Dist: numpydoc ; extra == 'docs'
Provides-Extra: tests
Requires-Dist: nose ; extra == 'tests'
